utcp_in_mem_embeddings/__init__.py
utcp_in_mem_embeddings/in_mem_embeddings_search.py
utcp_in_mem_embeddings-1.0.0.dist-info/METADATA
utcp_in_mem_embeddings-1.0.0.dist-info/WHEEL
utcp_in_mem_embeddings-1.0.0.dist-info/entry_points.txt
utcp_in_mem_embeddings-1.0.0.dist-info/top_level.txt
utcp_in_mem_embeddings-1.0.0.dist-info/RECORD
