Metadata-Version: 2.4
Name: utcp-in-mem-embeddings
Version: 1.0.0
Summary: UTCP plugin providing in-memory embedding-based semantic tool search.
Author: UTCP Contributors
License-Expression: MPL-2.0
Project-URL: Homepage, https://utcp.io
Project-URL: Source, https://github.com/universal-tool-calling-protocol/python-utcp
Project-URL: Issues, https://github.com/universal-tool-calling-protocol/python-utcp/issues
Classifier: Development Status :: 4 - Beta
Classifier: Intended Audience :: Developers
Classifier: Programming Language :: Python :: 3
Classifier: Operating System :: OS Independent
Requires-Python: >=3.10
Requires-Dist: pydantic>=2.0
Requires-Dist: utcp>=1.0
Requires-Dist: numpy>=2.3
Provides-Extra: embedding
Requires-Dist: sentence-transformers>=2.2.0; extra == "embedding"
Requires-Dist: torch>=1.9.0; extra == "embedding"
Provides-Extra: test
Requires-Dist: pytest>=7.0.0; extra == "test"
Requires-Dist: pytest-asyncio>=0.21.0; extra == "test"
